testo.py
kasane_testo-6.9.4.2.0.dist-info/licenses/LICENSE
kasane_testo-6.9.4.2.0.dist-info/METADATA
kasane_testo-6.9.4.2.0.dist-info/WHEEL
kasane_testo-6.9.4.2.0.dist-info/top_level.txt
kasane_testo-6.9.4.2.0.dist-info/RECORD
