Metadata-Version: 2.4
Name: kasane_testo
Version: 6.9.4.2.0
Summary: my first ever pypi package
Author-email: Moltony <koronavirusnyj@gmail.com>
License-Expression: MIT
Project-URL: Homepage, https://github.com/IAmMoltony/kasane-testo
Project-URL: Issues, https://github.com/IAmMoltony/kasane-testo/issues
Classifier: Programming Language :: Python :: 3
Classifier: Operating System :: OS Independent
Requires-Python: >=3.9
License-File: LICENSE
Dynamic: license-file
